LICENSE
README.md
setup.py
nceu/__init__.py
nceu/main.py
nceu.egg-info/PKG-INFO
nceu.egg-info/SOURCES.txt
nceu.egg-info/dependency_links.txt
nceu.egg-info/entry_points.txt
nceu.egg-info/requires.txt
nceu.egg-info/top_level.txt